[
{"datetime": "2021-05-30T23:49:30.020727Z", "matchtime": 0, "event": "KICKOFF", "payload": {"robot_name": "B3", "team_name": "B"}},
{"datetime": "2021-05-30T23:49:30.031329Z", "matchtime": 0, "event": "MATCH_START", "payload": {"score_yellow": 0, "score_blue": 0, "total_match_time": 600, "team_name_yellow": "i-bots 6", "team_name_blue": "ZTK Dubrovnik CRO team", "match_id": "qae_5_09", "halftime": 1}},
{"datetime": "2021-05-30T23:49:31.357243Z", "matchtime": 10.111999999994396, "event": "LACK_OF_PROGRESS", "payload": {"type": "ball"}},
{"datetime": "2021-05-30T23:49:32.129512Z", "matchtime": 15.103999999991629, "event": "LACK_OF_PROGRESS", "payload": {"type": "robot", "robot_name": "B1"}},
{"datetime": "2021-05-30T23:49:32.136199Z", "matchtime": 15.103999999991629, "event": "LACK_OF_PROGRESS", "payload": {"type": "robot", "robot_name": "B2"}},
{"datetime": "2021-05-30T23:49:32.141339Z", "matchtime": 15.103999999991629, "event": "LACK_OF_PROGRESS", "payload": {"type": "robot", "robot_name": "B3"}},
{"datetime": "2021-05-30T23:49:32.146530Z", "matchtime": 15.103999999991629, "event": "LACK_OF_PROGRESS", "payload": {"type": "robot", "robot_name": "Y1"}},
{"datetime": "2021-05-30T23:49:32.150552Z", "matchtime": 15.103999999991629, "event": "LACK_OF_PROGRESS", "payload": {"type": "robot", "robot_name": "Y2"}},
{"datetime": "2021-05-30T23:49:32.155519Z", "matchtime": 15.103999999991629, "event": "LACK_OF_PROGRESS", "payload": {"type": "robot", "robot_name": "Y3"}},
{"datetime": "2021-05-30T23:49:33.823877Z", "matchtime": 20.22399999998879, "event": "LACK_OF_PROGRESS", "payload": {"type": "ball"}},
{"datetime": "2021-05-30T23:49:37.141775Z", "matchtime": 30.207999999983258, "event": "LACK_OF_PROGRESS", "payload": {"type": "robot", "robot_name": "B1"}},
{"datetime": "2021-05-30T23:49:37.148156Z", "matchtime": 30.207999999983258, "event": "LACK_OF_PROGRESS", "payload": {"type": "robot", "robot_name": "B2"}},
{"datetime": "2021-05-30T23:49:37.152767Z", "matchtime": 30.207999999983258, "event": "LACK_OF_PROGRESS", "payload": {"type": "robot", "robot_name": "B3"}},
{"datetime": "2021-05-30T23:49:37.157147Z", "matchtime": 30.207999999983258, "event": "LACK_OF_PROGRESS", "payload": {"type": "robot", "robot_name": "Y1"}},
{"datetime": "2021-05-30T23:49:37.162176Z", "matchtime": 30.207999999983258, "event": "LACK_OF_PROGRESS", "payload": {"type": "robot", "robot_name": "Y2"}},
{"datetime": "2021-05-30T23:49:37.166608Z", "matchtime": 30.207999999983258, "event": "LACK_OF_PROGRESS", "payload": {"type": "robot", "robot_name": "Y3"}},
{"datetime": "2021-05-30T23:49:37.243959Z", "matchtime": 30.335999999983187, "event": "LACK_OF_PROGRESS", "payload": {"type": "ball"}},
{"datetime": "2021-05-30T23:49:40.595106Z", "matchtime": 40.44799999997758, "event": "LACK_OF_PROGRESS", "payload": {"type": "ball"}},
{"datetime": "2021-05-30T23:49:42.183761Z", "matchtime": 45.31199999997489, "event": "LACK_OF_PROGRESS", "payload": {"type": "robot", "robot_name": "B1"}},
{"datetime": "2021-05-30T23:49:42.189873Z", "matchtime": 45.31199999997489, "event": "LACK_OF_PROGRESS", "payload": {"type": "robot", "robot_name": "B2"}},
{"datetime": "2021-05-30T23:49:42.199624Z", "matchtime": 45.31199999997489, "event": "LACK_OF_PROGRESS", "payload": {"type": "robot", "robot_name": "B3"}},
{"datetime": "2021-05-30T23:49:42.204307Z", "matchtime": 45.31199999997489, "event": "LACK_OF_PROGRESS", "payload": {"type": "robot", "robot_name": "Y1"}},
{"datetime": "2021-05-30T23:49:42.209171Z", "matchtime": 45.31199999997489, "event": "LACK_OF_PROGRESS", "payload": {"type": "robot", "robot_name": "Y2"}},
{"datetime": "2021-05-30T23:49:42.214978Z", "matchtime": 45.31199999997489, "event": "LACK_OF_PROGRESS", "payload": {"type": "robot", "robot_name": "Y3"}},
{"datetime": "2021-05-30T23:49:43.888497Z", "matchtime": 50.55999999997198, "event": "LACK_OF_PROGRESS", "payload": {"type": "ball"}},
{"datetime": "2021-05-30T23:49:47.072149Z", "matchtime": 60.415999999966516, "event": "LACK_OF_PROGRESS", "payload": {"type": "robot", "robot_name": "B1"}},
{"datetime": "2021-05-30T23:49:47.077852Z", "matchtime": 60.415999999966516, "event": "LACK_OF_PROGRESS", "payload": {"type": "robot", "robot_name": "B2"}},
{"datetime": "2021-05-30T23:49:47.083120Z", "matchtime": 60.415999999966516, "event": "LACK_OF_PROGRESS", "payload": {"type": "robot", "robot_name": "B3"}},
{"datetime": "2021-05-30T23:49:47.087770Z", "matchtime": 60.415999999966516, "event": "LACK_OF_PROGRESS", "payload": {"type": "robot", "robot_name": "Y1"}},
{"datetime": "2021-05-30T23:49:47.092282Z", "matchtime": 60.415999999966516, "event": "LACK_OF_PROGRESS", "payload": {"type": "robot", "robot_name": "Y2"}},
{"datetime": "2021-05-30T23:49:47.097454Z", "matchtime": 60.415999999966516, "event": "LACK_OF_PROGRESS", "payload": {"type": "robot", "robot_name": "Y3"}},
{"datetime": "2021-05-30T23:49:47.183934Z", "matchtime": 60.671999999966374, "event": "LACK_OF_PROGRESS", "payload": {"type": "ball"}},
{"datetime": "2021-05-30T23:49:50.613761Z", "matchtime": 70.78399999996077, "event": "LACK_OF_PROGRESS", "payload": {"type": "ball"}},
{"datetime": "2021-05-30T23:49:52.204288Z", "matchtime": 75.51999999995815, "event": "LACK_OF_PROGRESS", "payload": {"type": "robot", "robot_name": "B1"}},
{"datetime": "2021-05-30T23:49:52.210125Z", "matchtime": 75.51999999995815, "event": "LACK_OF_PROGRESS", "payload": {"type": "robot", "robot_name": "B2"}},
{"datetime": "2021-05-30T23:49:52.215242Z", "matchtime": 75.51999999995815, "event": "LACK_OF_PROGRESS", "payload": {"type": "robot", "robot_name": "B3"}},
{"datetime": "2021-05-30T23:49:52.220314Z", "matchtime": 75.51999999995815, "event": "LACK_OF_PROGRESS", "payload": {"type": "robot", "robot_name": "Y1"}},
{"datetime": "2021-05-30T23:49:52.225750Z", "matchtime": 75.51999999995815, "event": "LACK_OF_PROGRESS", "payload": {"type": "robot", "robot_name": "Y2"}},
{"datetime": "2021-05-30T23:49:52.230303Z", "matchtime": 75.51999999995815, "event": "LACK_OF_PROGRESS", "payload": {"type": "robot", "robot_name": "Y3"}},
{"datetime": "2021-05-30T23:49:54.055430Z", "matchtime": 80.89599999995517, "event": "LACK_OF_PROGRESS", "payload": {"type": "ball"}},
{"datetime": "2021-05-30T23:49:57.299631Z", "matchtime": 90.6239999999521, "event": "LACK_OF_PROGRESS", "payload": {"type": "robot", "robot_name": "B1"}},
{"datetime": "2021-05-30T23:49:57.305860Z", "matchtime": 90.6239999999521, "event": "LACK_OF_PROGRESS", "payload": {"type": "robot", "robot_name": "B2"}},
{"datetime": "2021-05-30T23:49:57.310124Z", "matchtime": 90.6239999999521, "event": "LACK_OF_PROGRESS", "payload": {"type": "robot", "robot_name": "B3"}},
{"datetime": "2021-05-30T23:49:57.314991Z", "matchtime": 90.6239999999521, "event": "LACK_OF_PROGRESS", "payload": {"type": "robot", "robot_name": "Y1"}},
{"datetime": "2021-05-30T23:49:57.319828Z", "matchtime": 90.6239999999521, "event": "LACK_OF_PROGRESS", "payload": {"type": "robot", "robot_name": "Y2"}},
{"datetime": "2021-05-30T23:49:57.324194Z", "matchtime": 90.6239999999521, "event": "LACK_OF_PROGRESS", "payload": {"type": "robot", "robot_name": "Y3"}},
{"datetime": "2021-05-30T23:49:57.479299Z", "matchtime": 91.00799999995223, "event": "LACK_OF_PROGRESS", "payload": {"type": "ball"}},
{"datetime": "2021-05-30T23:50:00.826515Z", "matchtime": 101.11999999995561, "event": "LACK_OF_PROGRESS", "payload": {"type": "ball"}},
{"datetime": "2021-05-30T23:50:02.426076Z", "matchtime": 105.72799999995715, "event": "LACK_OF_PROGRESS", "payload": {"type": "robot", "robot_name": "B1"}},
{"datetime": "2021-05-30T23:50:02.431996Z", "matchtime": 105.72799999995715, "event": "LACK_OF_PROGRESS", "payload": {"type": "robot", "robot_name": "B2"}},
{"datetime": "2021-05-30T23:50:02.437399Z", "matchtime": 105.72799999995715, "event": "LACK_OF_PROGRESS", "payload": {"type": "robot", "robot_name": "B3"}},
{"datetime": "2021-05-30T23:50:02.442511Z", "matchtime": 105.72799999995715, "event": "LACK_OF_PROGRESS", "payload": {"type": "robot", "robot_name": "Y1"}},
{"datetime": "2021-05-30T23:50:02.447124Z", "matchtime": 105.72799999995715, "event": "LACK_OF_PROGRESS", "payload": {"type": "robot", "robot_name": "Y2"}},
{"datetime": "2021-05-30T23:50:02.452007Z", "matchtime": 105.72799999995715, "event": "LACK_OF_PROGRESS", "payload": {"type": "robot", "robot_name": "Y3"}},
{"datetime": "2021-05-30T23:50:04.297447Z", "matchtime": 111.23199999995899, "event": "LACK_OF_PROGRESS", "payload": {"type": "ball"}},
{"datetime": "2021-05-30T23:50:07.474336Z", "matchtime": 120.83199999996219, "event": "LACK_OF_PROGRESS", "payload": {"type": "robot", "robot_name": "B1"}},
{"datetime": "2021-05-30T23:50:07.479960Z", "matchtime": 120.83199999996219, "event": "LACK_OF_PROGRESS", "payload": {"type": "robot", "robot_name": "B2"}},
{"datetime": "2021-05-30T23:50:07.484734Z", "matchtime": 120.83199999996219, "event": "LACK_OF_PROGRESS", "payload": {"type": "robot", "robot_name": "B3"}},
{"datetime": "2021-05-30T23:50:07.488793Z", "matchtime": 120.83199999996219, "event": "LACK_OF_PROGRESS", "payload": {"type": "robot", "robot_name": "Y1"}},
{"datetime": "2021-05-30T23:50:07.493041Z", "matchtime": 120.83199999996219, "event": "LACK_OF_PROGRESS", "payload": {"type": "robot", "robot_name": "Y2"}},
{"datetime": "2021-05-30T23:50:07.497433Z", "matchtime": 120.83199999996219, "event": "LACK_OF_PROGRESS", "payload": {"type": "robot", "robot_name": "Y3"}},
{"datetime": "2021-05-30T23:50:07.663882Z", "matchtime": 121.34399999996236, "event": "LACK_OF_PROGRESS", "payload": {"type": "ball"}},
{"datetime": "2021-05-30T23:50:11.066727Z", "matchtime": 131.45599999996574, "event": "LACK_OF_PROGRESS", "payload": {"type": "ball"}},
{"datetime": "2021-05-30T23:50:12.513884Z", "matchtime": 135.93599999996724, "event": "LACK_OF_PROGRESS", "payload": {"type": "robot", "robot_name": "B1"}},
{"datetime": "2021-05-30T23:50:12.519869Z", "matchtime": 135.93599999996724, "event": "LACK_OF_PROGRESS", "payload": {"type": "robot", "robot_name": "B2"}},
{"datetime": "2021-05-30T23:50:12.525548Z", "matchtime": 135.93599999996724, "event": "LACK_OF_PROGRESS", "payload": {"type": "robot", "robot_name": "B3"}},
{"datetime": "2021-05-30T23:50:12.530553Z", "matchtime": 135.93599999996724, "event": "LACK_OF_PROGRESS", "payload": {"type": "robot", "robot_name": "Y1"}},
{"datetime": "2021-05-30T23:50:12.535129Z", "matchtime": 135.93599999996724, "event": "LACK_OF_PROGRESS", "payload": {"type": "robot", "robot_name": "Y2"}},
{"datetime": "2021-05-30T23:50:12.540123Z", "matchtime": 135.93599999996724, "event": "LACK_OF_PROGRESS", "payload": {"type": "robot", "robot_name": "Y3"}},
{"datetime": "2021-05-30T23:50:14.323128Z", "matchtime": 141.56799999996912, "event": "LACK_OF_PROGRESS", "payload": {"type": "ball"}},
{"datetime": "2021-05-30T23:50:17.351447Z", "matchtime": 151.03999999997228, "event": "LACK_OF_PROGRESS", "payload": {"type": "robot", "robot_name": "B1"}},
{"datetime": "2021-05-30T23:50:17.357079Z", "matchtime": 151.03999999997228, "event": "LACK_OF_PROGRESS", "payload": {"type": "robot", "robot_name": "B2"}},
{"datetime": "2021-05-30T23:50:17.362685Z", "matchtime": 151.03999999997228, "event": "LACK_OF_PROGRESS", "payload": {"type": "robot", "robot_name": "B3"}},
{"datetime": "2021-05-30T23:50:17.367824Z", "matchtime": 151.03999999997228, "event": "LACK_OF_PROGRESS", "payload": {"type": "robot", "robot_name": "Y1"}},
{"datetime": "2021-05-30T23:50:17.372423Z", "matchtime": 151.03999999997228, "event": "LACK_OF_PROGRESS", "payload": {"type": "robot", "robot_name": "Y2"}},
{"datetime": "2021-05-30T23:50:17.376763Z", "matchtime": 151.03999999997228, "event": "LACK_OF_PROGRESS", "payload": {"type": "robot", "robot_name": "Y3"}},
{"datetime": "2021-05-30T23:50:17.612347Z", "matchtime": 151.6799999999725, "event": "LACK_OF_PROGRESS", "payload": {"type": "ball"}},
{"datetime": "2021-05-30T23:50:20.876879Z", "matchtime": 161.79199999997587, "event": "LACK_OF_PROGRESS", "payload": {"type": "ball"}},
{"datetime": "2021-05-30T23:50:22.302596Z", "matchtime": 166.14399999997732, "event": "LACK_OF_PROGRESS", "payload": {"type": "robot", "robot_name": "B1"}},
{"datetime": "2021-05-30T23:50:22.307553Z", "matchtime": 166.14399999997732, "event": "LACK_OF_PROGRESS", "payload": {"type": "robot", "robot_name": "B2"}},
{"datetime": "2021-05-30T23:50:22.313873Z", "matchtime": 166.14399999997732, "event": "LACK_OF_PROGRESS", "payload": {"type": "robot", "robot_name": "B3"}},
{"datetime": "2021-05-30T23:50:22.318516Z", "matchtime": 166.14399999997732, "event": "LACK_OF_PROGRESS", "payload": {"type": "robot", "robot_name": "Y1"}},
{"datetime": "2021-05-30T23:50:22.323190Z", "matchtime": 166.14399999997732, "event": "LACK_OF_PROGRESS", "payload": {"type": "robot", "robot_name": "Y2"}},
{"datetime": "2021-05-30T23:50:22.329489Z", "matchtime": 166.14399999997732, "event": "LACK_OF_PROGRESS", "payload": {"type": "robot", "robot_name": "Y3"}},
{"datetime": "2021-05-30T23:50:24.176991Z", "matchtime": 171.90399999997925, "event": "LACK_OF_PROGRESS", "payload": {"type": "ball"}},
{"datetime": "2021-05-30T23:50:27.188207Z", "matchtime": 181.24799999998237, "event": "LACK_OF_PROGRESS", "payload": {"type": "robot", "robot_name": "B1"}},
{"datetime": "2021-05-30T23:50:27.195017Z", "matchtime": 181.24799999998237, "event": "LACK_OF_PROGRESS", "payload": {"type": "robot", "robot_name": "B2"}},
{"datetime": "2021-05-30T23:50:27.200940Z", "matchtime": 181.24799999998237, "event": "LACK_OF_PROGRESS", "payload": {"type": "robot", "robot_name": "B3"}},
{"datetime": "2021-05-30T23:50:27.206330Z", "matchtime": 181.24799999998237, "event": "LACK_OF_PROGRESS", "payload": {"type": "robot", "robot_name": "Y1"}},
{"datetime": "2021-05-30T23:50:27.212512Z", "matchtime": 181.24799999998237, "event": "LACK_OF_PROGRESS", "payload": {"type": "robot", "robot_name": "Y2"}},
{"datetime": "2021-05-30T23:50:27.217541Z", "matchtime": 181.24799999998237, "event": "LACK_OF_PROGRESS", "payload": {"type": "robot", "robot_name": "Y3"}},
{"datetime": "2021-05-30T23:50:27.526739Z", "matchtime": 182.01599999998263, "event": "LACK_OF_PROGRESS", "payload": {"type": "ball"}},
{"datetime": "2021-05-30T23:50:30.904927Z", "matchtime": 192.127999999986, "event": "LACK_OF_PROGRESS", "payload": {"type": "ball"}},
{"datetime": "2021-05-30T23:50:32.339994Z", "matchtime": 196.3519999999874, "event": "LACK_OF_PROGRESS", "payload": {"type": "robot", "robot_name": "B1"}},
{"datetime": "2021-05-30T23:50:32.345653Z", "matchtime": 196.3519999999874, "event": "LACK_OF_PROGRESS", "payload": {"type": "robot", "robot_name": "B2"}},
{"datetime": "2021-05-30T23:50:32.349814Z", "matchtime": 196.3519999999874, "event": "LACK_OF_PROGRESS", "payload": {"type": "robot", "robot_name": "B3"}},
{"datetime": "2021-05-30T23:50:32.354365Z", "matchtime": 196.3519999999874, "event": "LACK_OF_PROGRESS", "payload": {"type": "robot", "robot_name": "Y1"}},
{"datetime": "2021-05-30T23:50:32.359413Z", "matchtime": 196.3519999999874, "event": "LACK_OF_PROGRESS", "payload": {"type": "robot", "robot_name": "Y2"}},
{"datetime": "2021-05-30T23:50:32.364452Z", "matchtime": 196.3519999999874, "event": "LACK_OF_PROGRESS", "payload": {"type": "robot", "robot_name": "Y3"}},
{"datetime": "2021-05-30T23:50:34.374562Z", "matchtime": 202.23999999998938, "event": "LACK_OF_PROGRESS", "payload": {"type": "ball"}},
{"datetime": "2021-05-30T23:50:37.499963Z", "matchtime": 211.45599999999246, "event": "LACK_OF_PROGRESS", "payload": {"type": "robot", "robot_name": "B1"}},
{"datetime": "2021-05-30T23:50:37.505911Z", "matchtime": 211.45599999999246, "event": "LACK_OF_PROGRESS", "payload": {"type": "robot", "robot_name": "B2"}},
{"datetime": "2021-05-30T23:50:37.510631Z", "matchtime": 211.45599999999246, "event": "LACK_OF_PROGRESS", "payload": {"type": "robot", "robot_name": "B3"}},
{"datetime": "2021-05-30T23:50:37.514673Z", "matchtime": 211.45599999999246, "event": "LACK_OF_PROGRESS", "payload": {"type": "robot", "robot_name": "Y1"}},
{"datetime": "2021-05-30T23:50:37.519405Z", "matchtime": 211.45599999999246, "event": "LACK_OF_PROGRESS", "payload": {"type": "robot", "robot_name": "Y2"}},
{"datetime": "2021-05-30T23:50:37.524313Z", "matchtime": 211.45599999999246, "event": "LACK_OF_PROGRESS", "payload": {"type": "robot", "robot_name": "Y3"}},
{"datetime": "2021-05-30T23:50:37.841882Z", "matchtime": 212.35199999999276, "event": "LACK_OF_PROGRESS", "payload": {"type": "ball"}},
{"datetime": "2021-05-30T23:50:41.250946Z", "matchtime": 222.46399999999613, "event": "LACK_OF_PROGRESS", "payload": {"type": "ball"}},
{"datetime": "2021-05-30T23:50:42.596526Z", "matchtime": 226.5599999999975, "event": "LACK_OF_PROGRESS", "payload": {"type": "robot", "robot_name": "B1"}},
{"datetime": "2021-05-30T23:50:42.602929Z", "matchtime": 226.5599999999975, "event": "LACK_OF_PROGRESS", "payload": {"type": "robot", "robot_name": "B2"}},
{"datetime": "2021-05-30T23:50:42.608065Z", "matchtime": 226.5599999999975, "event": "LACK_OF_PROGRESS", "payload": {"type": "robot", "robot_name": "B3"}},
{"datetime": "2021-05-30T23:50:42.612988Z", "matchtime": 226.5599999999975, "event": "LACK_OF_PROGRESS", "payload": {"type": "robot", "robot_name": "Y1"}},
{"datetime": "2021-05-30T23:50:42.617815Z", "matchtime": 226.5599999999975, "event": "LACK_OF_PROGRESS", "payload": {"type": "robot", "robot_name": "Y2"}},
{"datetime": "2021-05-30T23:50:42.623156Z", "matchtime": 226.5599999999975, "event": "LACK_OF_PROGRESS", "payload": {"type": "robot", "robot_name": "Y3"}},
{"datetime": "2021-05-30T23:50:44.611416Z", "matchtime": 232.5759999999995, "event": "LACK_OF_PROGRESS", "payload": {"type": "ball"}},
{"datetime": "2021-05-30T23:50:47.644787Z", "matchtime": 241.66400000000255, "event": "LACK_OF_PROGRESS", "payload": {"type": "robot", "robot_name": "B1"}},
{"datetime": "2021-05-30T23:50:47.650756Z", "matchtime": 241.66400000000255, "event": "LACK_OF_PROGRESS", "payload": {"type": "robot", "robot_name": "B2"}},
{"datetime": "2021-05-30T23:50:47.655849Z", "matchtime": 241.66400000000255, "event": "LACK_OF_PROGRESS", "payload": {"type": "robot", "robot_name": "B3"}},
{"datetime": "2021-05-30T23:50:47.661152Z", "matchtime": 241.66400000000255, "event": "LACK_OF_PROGRESS", "payload": {"type": "robot", "robot_name": "Y1"}},
{"datetime": "2021-05-30T23:50:47.665960Z", "matchtime": 241.66400000000255, "event": "LACK_OF_PROGRESS", "payload": {"type": "robot", "robot_name": "Y2"}},
{"datetime": "2021-05-30T23:50:47.671000Z", "matchtime": 241.66400000000255, "event": "LACK_OF_PROGRESS", "payload": {"type": "robot", "robot_name": "Y3"}},
{"datetime": "2021-05-30T23:50:48.059490Z", "matchtime": 242.6880000000029, "event": "LACK_OF_PROGRESS", "payload": {"type": "ball"}},
{"datetime": "2021-05-30T23:50:51.431125Z", "matchtime": 252.80000000000626, "event": "LACK_OF_PROGRESS", "payload": {"type": "ball"}},
{"datetime": "2021-05-30T23:50:52.795786Z", "matchtime": 256.7680000000076, "event": "LACK_OF_PROGRESS", "payload": {"type": "robot", "robot_name": "B1"}},
{"datetime": "2021-05-30T23:50:52.801083Z", "matchtime": 256.7680000000076, "event": "LACK_OF_PROGRESS", "payload": {"type": "robot", "robot_name": "B2"}},
{"datetime": "2021-05-30T23:50:52.806529Z", "matchtime": 256.7680000000076, "event": "LACK_OF_PROGRESS", "payload": {"type": "robot", "robot_name": "B3"}},
{"datetime": "2021-05-30T23:50:52.811519Z", "matchtime": 256.7680000000076, "event": "LACK_OF_PROGRESS", "payload": {"type": "robot", "robot_name": "Y1"}},
{"datetime": "2021-05-30T23:50:52.816548Z", "matchtime": 256.7680000000076, "event": "LACK_OF_PROGRESS", "payload": {"type": "robot", "robot_name": "Y2"}},
{"datetime": "2021-05-30T23:50:52.822292Z", "matchtime": 256.7680000000076, "event": "LACK_OF_PROGRESS", "payload": {"type": "robot", "robot_name": "Y3"}},
{"datetime": "2021-05-30T23:50:54.904772Z", "matchtime": 262.91200000000964, "event": "LACK_OF_PROGRESS", "payload": {"type": "ball"}},
{"datetime": "2021-05-30T23:50:57.809556Z", "matchtime": 271.87200000001263, "event": "LACK_OF_PROGRESS", "payload": {"type": "robot", "robot_name": "B1"}},
{"datetime": "2021-05-30T23:50:57.815404Z", "matchtime": 271.87200000001263, "event": "LACK_OF_PROGRESS", "payload": {"type": "robot", "robot_name": "B2"}},
{"datetime": "2021-05-30T23:50:57.820192Z", "matchtime": 271.87200000001263, "event": "LACK_OF_PROGRESS", "payload": {"type": "robot", "robot_name": "B3"}},
{"datetime": "2021-05-30T23:50:57.824933Z", "matchtime": 271.87200000001263, "event": "LACK_OF_PROGRESS", "payload": {"type": "robot", "robot_name": "Y1"}},
{"datetime": "2021-05-30T23:50:57.829969Z", "matchtime": 271.87200000001263, "event": "LACK_OF_PROGRESS", "payload": {"type": "robot", "robot_name": "Y2"}},
{"datetime": "2021-05-30T23:50:57.837701Z", "matchtime": 271.87200000001263, "event": "LACK_OF_PROGRESS", "payload": {"type": "robot", "robot_name": "Y3"}},
{"datetime": "2021-05-30T23:50:58.238662Z", "matchtime": 273.024000000013, "event": "LACK_OF_PROGRESS", "payload": {"type": "ball"}},
{"datetime": "2021-05-30T23:51:01.602644Z", "matchtime": 283.1360000000164, "event": "LACK_OF_PROGRESS", "payload": {"type": "ball"}},
{"datetime": "2021-05-30T23:51:02.890923Z", "matchtime": 286.9760000000177, "event": "LACK_OF_PROGRESS", "payload": {"type": "robot", "robot_name": "B1"}},
{"datetime": "2021-05-30T23:51:02.898039Z", "matchtime": 286.9760000000177, "event": "LACK_OF_PROGRESS", "payload": {"type": "robot", "robot_name": "B2"}},
{"datetime": "2021-05-30T23:51:02.903032Z", "matchtime": 286.9760000000177, "event": "LACK_OF_PROGRESS", "payload": {"type": "robot", "robot_name": "B3"}},
{"datetime": "2021-05-30T23:51:02.908311Z", "matchtime": 286.9760000000177, "event": "LACK_OF_PROGRESS", "payload": {"type": "robot", "robot_name": "Y1"}},
{"datetime": "2021-05-30T23:51:02.912852Z", "matchtime": 286.9760000000177, "event": "LACK_OF_PROGRESS", "payload": {"type": "robot", "robot_name": "Y2"}},
{"datetime": "2021-05-30T23:51:02.917819Z", "matchtime": 286.9760000000177, "event": "LACK_OF_PROGRESS", "payload": {"type": "robot", "robot_name": "Y3"}},
{"datetime": "2021-05-30T23:51:05.068326Z", "matchtime": 293.2480000000198, "event": "LACK_OF_PROGRESS", "payload": {"type": "ball"}},
{"datetime": "2021-05-30T23:51:07.878082Z", "matchtime": 302.0800000000227, "event": "LACK_OF_PROGRESS", "payload": {"type": "robot", "robot_name": "B1"}},
{"datetime": "2021-05-30T23:51:07.883897Z", "matchtime": 302.0800000000227, "event": "LACK_OF_PROGRESS", "payload": {"type": "robot", "robot_name": "B2"}},
{"datetime": "2021-05-30T23:51:07.888946Z", "matchtime": 302.0800000000227, "event": "LACK_OF_PROGRESS", "payload": {"type": "robot", "robot_name": "B3"}},
{"datetime": "2021-05-30T23:51:07.893804Z", "matchtime": 302.0800000000227, "event": "LACK_OF_PROGRESS", "payload": {"type": "robot", "robot_name": "Y1"}},
{"datetime": "2021-05-30T23:51:07.898569Z", "matchtime": 302.0800000000227, "event": "LACK_OF_PROGRESS", "payload": {"type": "robot", "robot_name": "Y2"}},
{"datetime": "2021-05-30T23:51:07.903126Z", "matchtime": 302.0800000000227, "event": "LACK_OF_PROGRESS", "payload": {"type": "robot", "robot_name": "Y3"}},
{"datetime": "2021-05-30T23:51:08.318748Z", "matchtime": 303.36000000002315, "event": "LACK_OF_PROGRESS", "payload": {"type": "ball"}},
{"datetime": "2021-05-30T23:51:11.602075Z", "matchtime": 313.4720000000265, "event": "LACK_OF_PROGRESS", "payload": {"type": "ball"}},
{"datetime": "2021-05-30T23:51:12.805062Z", "matchtime": 317.18400000002777, "event": "LACK_OF_PROGRESS", "payload": {"type": "robot", "robot_name": "B1"}},
{"datetime": "2021-05-30T23:51:12.811529Z", "matchtime": 317.18400000002777, "event": "LACK_OF_PROGRESS", "payload": {"type": "robot", "robot_name": "B2"}},
{"datetime": "2021-05-30T23:51:12.816757Z", "matchtime": 317.18400000002777, "event": "LACK_OF_PROGRESS", "payload": {"type": "robot", "robot_name": "B3"}},
{"datetime": "2021-05-30T23:51:12.821456Z", "matchtime": 317.18400000002777, "event": "LACK_OF_PROGRESS", "payload": {"type": "robot", "robot_name": "Y1"}},
{"datetime": "2021-05-30T23:51:12.826475Z", "matchtime": 317.18400000002777, "event": "LACK_OF_PROGRESS", "payload": {"type": "robot", "robot_name": "Y2"}},
{"datetime": "2021-05-30T23:51:12.831345Z", "matchtime": 317.18400000002777, "event": "LACK_OF_PROGRESS", "payload": {"type": "robot", "robot_name": "Y3"}},
{"datetime": "2021-05-30T23:51:14.904415Z", "matchtime": 323.5840000000299, "event": "LACK_OF_PROGRESS", "payload": {"type": "ball"}},
{"datetime": "2021-05-30T23:51:17.632982Z", "matchtime": 332.2880000000328, "event": "LACK_OF_PROGRESS", "payload": {"type": "robot", "robot_name": "B1"}},
{"datetime": "2021-05-30T23:51:17.638840Z", "matchtime": 332.2880000000328, "event": "LACK_OF_PROGRESS", "payload": {"type": "robot", "robot_name": "B2"}},
{"datetime": "2021-05-30T23:51:17.644895Z", "matchtime": 332.2880000000328, "event": "LACK_OF_PROGRESS", "payload": {"type": "robot", "robot_name": "B3"}},
{"datetime": "2021-05-30T23:51:17.650240Z", "matchtime": 332.2880000000328, "event": "LACK_OF_PROGRESS", "payload": {"type": "robot", "robot_name": "Y1"}},
{"datetime": "2021-05-30T23:51:17.655648Z", "matchtime": 332.2880000000328, "event": "LACK_OF_PROGRESS", "payload": {"type": "robot", "robot_name": "Y2"}},
{"datetime": "2021-05-30T23:51:17.660604Z", "matchtime": 332.2880000000328, "event": "LACK_OF_PROGRESS", "payload": {"type": "robot", "robot_name": "Y3"}},
{"datetime": "2021-05-30T23:51:18.136421Z", "matchtime": 333.6960000000333, "event": "LACK_OF_PROGRESS", "payload": {"type": "ball"}},
{"datetime": "2021-05-30T23:51:21.337679Z", "matchtime": 343.80800000003666, "event": "LACK_OF_PROGRESS", "payload": {"type": "ball"}},
{"datetime": "2021-05-30T23:51:22.466742Z", "matchtime": 347.3920000000363, "event": "LACK_OF_PROGRESS", "payload": {"type": "robot", "robot_name": "B1"}},
{"datetime": "2021-05-30T23:51:22.472726Z", "matchtime": 347.3920000000363, "event": "LACK_OF_PROGRESS", "payload": {"type": "robot", "robot_name": "B2"}},
{"datetime": "2021-05-30T23:51:22.477829Z", "matchtime": 347.3920000000363, "event": "LACK_OF_PROGRESS", "payload": {"type": "robot", "robot_name": "B3"}},
{"datetime": "2021-05-30T23:51:22.482481Z", "matchtime": 347.3920000000363, "event": "LACK_OF_PROGRESS", "payload": {"type": "robot", "robot_name": "Y1"}},
{"datetime": "2021-05-30T23:51:22.486971Z", "matchtime": 347.3920000000363, "event": "LACK_OF_PROGRESS", "payload": {"type": "robot", "robot_name": "Y2"}},
{"datetime": "2021-05-30T23:51:22.492070Z", "matchtime": 347.3920000000363, "event": "LACK_OF_PROGRESS", "payload": {"type": "robot", "robot_name": "Y3"}},
{"datetime": "2021-05-30T23:51:24.575783Z", "matchtime": 353.9200000000356, "event": "LACK_OF_PROGRESS", "payload": {"type": "ball"}},
{"datetime": "2021-05-30T23:51:27.291446Z", "matchtime": 362.49600000003466, "event": "LACK_OF_PROGRESS", "payload": {"type": "robot", "robot_name": "B1"}},
{"datetime": "2021-05-30T23:51:27.297254Z", "matchtime": 362.49600000003466, "event": "LACK_OF_PROGRESS", "payload": {"type": "robot", "robot_name": "B2"}},
{"datetime": "2021-05-30T23:51:27.302295Z", "matchtime": 362.49600000003466, "event": "LACK_OF_PROGRESS", "payload": {"type": "robot", "robot_name": "B3"}},
{"datetime": "2021-05-30T23:51:27.307238Z", "matchtime": 362.49600000003466, "event": "LACK_OF_PROGRESS", "payload": {"type": "robot", "robot_name": "Y1"}},
{"datetime": "2021-05-30T23:51:27.316424Z", "matchtime": 362.49600000003466, "event": "LACK_OF_PROGRESS", "payload": {"type": "robot", "robot_name": "Y2"}},
{"datetime": "2021-05-30T23:51:27.321137Z", "matchtime": 362.49600000003466, "event": "LACK_OF_PROGRESS", "payload": {"type": "robot", "robot_name": "Y3"}},
{"datetime": "2021-05-30T23:51:27.803014Z", "matchtime": 364.0320000000345, "event": "LACK_OF_PROGRESS", "payload": {"type": "ball"}},
{"datetime": "2021-05-30T23:51:31.069631Z", "matchtime": 374.1440000000334, "event": "LACK_OF_PROGRESS", "payload": {"type": "ball"}},
{"datetime": "2021-05-30T23:51:32.190471Z", "matchtime": 377.600000000033, "event": "LACK_OF_PROGRESS", "payload": {"type": "robot", "robot_name": "B1"}},
{"datetime": "2021-05-30T23:51:32.196811Z", "matchtime": 377.600000000033, "event": "LACK_OF_PROGRESS", "payload": {"type": "robot", "robot_name": "B2"}},
{"datetime": "2021-05-30T23:51:32.201652Z", "matchtime": 377.600000000033, "event": "LACK_OF_PROGRESS", "payload": {"type": "robot", "robot_name": "B3"}},
{"datetime": "2021-05-30T23:51:32.206733Z", "matchtime": 377.600000000033, "event": "LACK_OF_PROGRESS", "payload": {"type": "robot", "robot_name": "Y1"}},
{"datetime": "2021-05-30T23:51:32.211488Z", "matchtime": 377.600000000033, "event": "LACK_OF_PROGRESS", "payload": {"type": "robot", "robot_name": "Y2"}},
{"datetime": "2021-05-30T23:51:32.216178Z", "matchtime": 377.600000000033, "event": "LACK_OF_PROGRESS", "payload": {"type": "robot", "robot_name": "Y3"}},
{"datetime": "2021-05-30T23:51:34.446188Z", "matchtime": 384.25600000003226, "event": "LACK_OF_PROGRESS", "payload": {"type": "ball"}},
{"datetime": "2021-05-30T23:51:37.162153Z", "matchtime": 392.70400000003133, "event": "LACK_OF_PROGRESS", "payload": {"type": "robot", "robot_name": "B1"}},
{"datetime": "2021-05-30T23:51:37.167857Z", "matchtime": 392.70400000003133, "event": "LACK_OF_PROGRESS", "payload": {"type": "robot", "robot_name": "B2"}},
{"datetime": "2021-05-30T23:51:37.172817Z", "matchtime": 392.70400000003133, "event": "LACK_OF_PROGRESS", "payload": {"type": "robot", "robot_name": "B3"}},
{"datetime": "2021-05-30T23:51:37.177543Z", "matchtime": 392.70400000003133, "event": "LACK_OF_PROGRESS", "payload": {"type": "robot", "robot_name": "Y1"}},
{"datetime": "2021-05-30T23:51:37.181791Z", "matchtime": 392.70400000003133, "event": "LACK_OF_PROGRESS", "payload": {"type": "robot", "robot_name": "Y2"}},
{"datetime": "2021-05-30T23:51:37.186592Z", "matchtime": 392.70400000003133, "event": "LACK_OF_PROGRESS", "payload": {"type": "robot", "robot_name": "Y3"}},
{"datetime": "2021-05-30T23:51:37.750020Z", "matchtime": 394.36800000003115, "event": "LACK_OF_PROGRESS", "payload": {"type": "ball"}},
{"datetime": "2021-05-30T23:51:41.114103Z", "matchtime": 404.48000000003003, "event": "LACK_OF_PROGRESS", "payload": {"type": "ball"}},
{"datetime": "2021-05-30T23:51:42.233442Z", "matchtime": 407.80800000002966, "event": "LACK_OF_PROGRESS", "payload": {"type": "robot", "robot_name": "B1"}},
{"datetime": "2021-05-30T23:51:42.239224Z", "matchtime": 407.80800000002966, "event": "LACK_OF_PROGRESS", "payload": {"type": "robot", "robot_name": "B2"}},
{"datetime": "2021-05-30T23:51:42.244867Z", "matchtime": 407.80800000002966, "event": "LACK_OF_PROGRESS", "payload": {"type": "robot", "robot_name": "B3"}},
{"datetime": "2021-05-30T23:51:42.251463Z", "matchtime": 407.80800000002966, "event": "LACK_OF_PROGRESS", "payload": {"type": "robot", "robot_name": "Y1"}},
{"datetime": "2021-05-30T23:51:42.256838Z", "matchtime": 407.80800000002966, "event": "LACK_OF_PROGRESS", "payload": {"type": "robot", "robot_name": "Y2"}},
{"datetime": "2021-05-30T23:51:42.262020Z", "matchtime": 407.80800000002966, "event": "LACK_OF_PROGRESS", "payload": {"type": "robot", "robot_name": "Y3"}},
{"datetime": "2021-05-30T23:51:44.483611Z", "matchtime": 414.5920000000289, "event": "LACK_OF_PROGRESS", "payload": {"type": "ball"}},
{"datetime": "2021-05-30T23:51:47.132098Z", "matchtime": 422.912000000028, "event": "LACK_OF_PROGRESS", "payload": {"type": "robot", "robot_name": "B1"}},
{"datetime": "2021-05-30T23:51:47.137867Z", "matchtime": 422.912000000028, "event": "LACK_OF_PROGRESS", "payload": {"type": "robot", "robot_name": "B2"}},
{"datetime": "2021-05-30T23:51:47.144757Z", "matchtime": 422.912000000028, "event": "LACK_OF_PROGRESS", "payload": {"type": "robot", "robot_name": "B3"}},
{"datetime": "2021-05-30T23:51:47.149704Z", "matchtime": 422.912000000028, "event": "LACK_OF_PROGRESS", "payload": {"type": "robot", "robot_name": "Y1"}},
{"datetime": "2021-05-30T23:51:47.154471Z", "matchtime": 422.912000000028, "event": "LACK_OF_PROGRESS", "payload": {"type": "robot", "robot_name": "Y2"}},
{"datetime": "2021-05-30T23:51:47.161138Z", "matchtime": 422.912000000028, "event": "LACK_OF_PROGRESS", "payload": {"type": "robot", "robot_name": "Y3"}},
{"datetime": "2021-05-30T23:51:47.793630Z", "matchtime": 424.7040000000278, "event": "LACK_OF_PROGRESS", "payload": {"type": "ball"}},
{"datetime": "2021-05-30T23:51:50.979169Z", "matchtime": 434.8160000000267, "event": "LACK_OF_PROGRESS", "payload": {"type": "ball"}},
{"datetime": "2021-05-30T23:51:52.015412Z", "matchtime": 438.01600000002634, "event": "LACK_OF_PROGRESS", "payload": {"type": "robot", "robot_name": "B1"}},
{"datetime": "2021-05-30T23:51:52.024474Z", "matchtime": 438.01600000002634, "event": "LACK_OF_PROGRESS", "payload": {"type": "robot", "robot_name": "B2"}},
{"datetime": "2021-05-30T23:51:52.029315Z", "matchtime": 438.01600000002634, "event": "LACK_OF_PROGRESS", "payload": {"type": "robot", "robot_name": "B3"}},
{"datetime": "2021-05-30T23:51:52.037705Z", "matchtime": 438.01600000002634, "event": "LACK_OF_PROGRESS", "payload": {"type": "robot", "robot_name": "Y1"}},
{"datetime": "2021-05-30T23:51:52.043201Z", "matchtime": 438.01600000002634, "event": "LACK_OF_PROGRESS", "payload": {"type": "robot", "robot_name": "Y2"}},
{"datetime": "2021-05-30T23:51:52.048390Z", "matchtime": 438.01600000002634, "event": "LACK_OF_PROGRESS", "payload": {"type": "robot", "robot_name": "Y3"}},
{"datetime": "2021-05-30T23:51:54.276817Z", "matchtime": 444.9280000000256, "event": "LACK_OF_PROGRESS", "payload": {"type": "ball"}},
{"datetime": "2021-05-30T23:51:56.832239Z", "matchtime": 453.1200000000247, "event": "LACK_OF_PROGRESS", "payload": {"type": "robot", "robot_name": "B1"}},
{"datetime": "2021-05-30T23:51:56.838035Z", "matchtime": 453.1200000000247, "event": "LACK_OF_PROGRESS", "payload": {"type": "robot", "robot_name": "B2"}},
{"datetime": "2021-05-30T23:51:56.843335Z", "matchtime": 453.1200000000247, "event": "LACK_OF_PROGRESS", "payload": {"type": "robot", "robot_name": "B3"}},
{"datetime": "2021-05-30T23:51:56.849151Z", "matchtime": 453.1200000000247, "event": "LACK_OF_PROGRESS", "payload": {"type": "robot", "robot_name": "Y1"}},
{"datetime": "2021-05-30T23:51:56.854023Z", "matchtime": 453.1200000000247, "event": "LACK_OF_PROGRESS", "payload": {"type": "robot", "robot_name": "Y2"}},
{"datetime": "2021-05-30T23:51:56.858852Z", "matchtime": 453.1200000000247, "event": "LACK_OF_PROGRESS", "payload": {"type": "robot", "robot_name": "Y3"}},
{"datetime": "2021-05-30T23:51:57.496754Z", "matchtime": 455.04000000002446, "event": "LACK_OF_PROGRESS", "payload": {"type": "ball"}},
{"datetime": "2021-05-30T23:52:00.862643Z", "matchtime": 465.15200000002335, "event": "LACK_OF_PROGRESS", "payload": {"type": "ball"}},
{"datetime": "2021-05-30T23:52:01.834148Z", "matchtime": 468.224000000023, "event": "LACK_OF_PROGRESS", "payload": {"type": "robot", "robot_name": "B1"}},
{"datetime": "2021-05-30T23:52:01.840868Z", "matchtime": 468.224000000023, "event": "LACK_OF_PROGRESS", "payload": {"type": "robot", "robot_name": "B2"}},
{"datetime": "2021-05-30T23:52:01.845928Z", "matchtime": 468.224000000023, "event": "LACK_OF_PROGRESS", "payload": {"type": "robot", "robot_name": "B3"}},
{"datetime": "2021-05-30T23:52:01.850932Z", "matchtime": 468.224000000023, "event": "LACK_OF_PROGRESS", "payload": {"type": "robot", "robot_name": "Y1"}},
{"datetime": "2021-05-30T23:52:01.855483Z", "matchtime": 468.224000000023, "event": "LACK_OF_PROGRESS", "payload": {"type": "robot", "robot_name": "Y2"}},
{"datetime": "2021-05-30T23:52:01.860210Z", "matchtime": 468.224000000023, "event": "LACK_OF_PROGRESS", "payload": {"type": "robot", "robot_name": "Y3"}},
{"datetime": "2021-05-30T23:52:04.092735Z", "matchtime": 475.26400000002224, "event": "LACK_OF_PROGRESS", "payload": {"type": "ball"}},
{"datetime": "2021-05-30T23:52:06.652082Z", "matchtime": 483.32800000002135, "event": "LACK_OF_PROGRESS", "payload": {"type": "robot", "robot_name": "B1"}},
{"datetime": "2021-05-30T23:52:06.658277Z", "matchtime": 483.32800000002135, "event": "LACK_OF_PROGRESS", "payload": {"type": "robot", "robot_name": "B2"}},
{"datetime": "2021-05-30T23:52:06.665098Z", "matchtime": 483.32800000002135, "event": "LACK_OF_PROGRESS", "payload": {"type": "robot", "robot_name": "B3"}},
{"datetime": "2021-05-30T23:52:06.669554Z", "matchtime": 483.32800000002135, "event": "LACK_OF_PROGRESS", "payload": {"type": "robot", "robot_name": "Y1"}},
{"datetime": "2021-05-30T23:52:06.674563Z", "matchtime": 483.32800000002135, "event": "LACK_OF_PROGRESS", "payload": {"type": "robot", "robot_name": "Y2"}},
{"datetime": "2021-05-30T23:52:06.679366Z", "matchtime": 483.32800000002135, "event": "LACK_OF_PROGRESS", "payload": {"type": "robot", "robot_name": "Y3"}},
{"datetime": "2021-05-30T23:52:07.400905Z", "matchtime": 485.3760000000211, "event": "LACK_OF_PROGRESS", "payload": {"type": "ball"}},
{"datetime": "2021-05-30T23:52:10.714853Z", "matchtime": 495.48800000002, "event": "LACK_OF_PROGRESS", "payload": {"type": "ball"}},
{"datetime": "2021-05-30T23:52:11.684187Z", "matchtime": 498.4320000000197, "event": "LACK_OF_PROGRESS", "payload": {"type": "robot", "robot_name": "B1"}},
{"datetime": "2021-05-30T23:52:11.690780Z", "matchtime": 498.4320000000197, "event": "LACK_OF_PROGRESS", "payload": {"type": "robot", "robot_name": "B2"}},
{"datetime": "2021-05-30T23:52:11.695693Z", "matchtime": 498.4320000000197, "event": "LACK_OF_PROGRESS", "payload": {"type": "robot", "robot_name": "B3"}},
{"datetime": "2021-05-30T23:52:11.700317Z", "matchtime": 498.4320000000197, "event": "LACK_OF_PROGRESS", "payload": {"type": "robot", "robot_name": "Y1"}},
{"datetime": "2021-05-30T23:52:11.705118Z", "matchtime": 498.4320000000197, "event": "LACK_OF_PROGRESS", "payload": {"type": "robot", "robot_name": "Y2"}},
{"datetime": "2021-05-30T23:52:11.709650Z", "matchtime": 498.4320000000197, "event": "LACK_OF_PROGRESS", "payload": {"type": "robot", "robot_name": "Y3"}},
{"datetime": "2021-05-30T23:52:14.010425Z", "matchtime": 505.6000000000189, "event": "LACK_OF_PROGRESS", "payload": {"type": "ball"}},
{"datetime": "2021-05-30T23:52:16.482574Z", "matchtime": 513.536000000018, "event": "LACK_OF_PROGRESS", "payload": {"type": "robot", "robot_name": "B1"}},
{"datetime": "2021-05-30T23:52:16.488199Z", "matchtime": 513.536000000018, "event": "LACK_OF_PROGRESS", "payload": {"type": "robot", "robot_name": "B2"}},
{"datetime": "2021-05-30T23:52:16.494640Z", "matchtime": 513.536000000018, "event": "LACK_OF_PROGRESS", "payload": {"type": "robot", "robot_name": "B3"}},
{"datetime": "2021-05-30T23:52:16.499998Z", "matchtime": 513.536000000018, "event": "LACK_OF_PROGRESS", "payload": {"type": "robot", "robot_name": "Y1"}},
{"datetime": "2021-05-30T23:52:16.506130Z", "matchtime": 513.536000000018, "event": "LACK_OF_PROGRESS", "payload": {"type": "robot", "robot_name": "Y2"}},
{"datetime": "2021-05-30T23:52:16.510603Z", "matchtime": 513.536000000018, "event": "LACK_OF_PROGRESS", "payload": {"type": "robot", "robot_name": "Y3"}},
{"datetime": "2021-05-30T23:52:17.227937Z", "matchtime": 515.7120000000177, "event": "LACK_OF_PROGRESS", "payload": {"type": "ball"}},
{"datetime": "2021-05-30T23:52:20.441814Z", "matchtime": 525.8240000000167, "event": "LACK_OF_PROGRESS", "payload": {"type": "ball"}},
{"datetime": "2021-05-30T23:52:21.324662Z", "matchtime": 528.6400000000164, "event": "LACK_OF_PROGRESS", "payload": {"type": "robot", "robot_name": "B1"}},
{"datetime": "2021-05-30T23:52:21.330249Z", "matchtime": 528.6400000000164, "event": "LACK_OF_PROGRESS", "payload": {"type": "robot", "robot_name": "B2"}},
{"datetime": "2021-05-30T23:52:21.335200Z", "matchtime": 528.6400000000164, "event": "LACK_OF_PROGRESS", "payload": {"type": "robot", "robot_name": "B3"}},
{"datetime": "2021-05-30T23:52:21.339928Z", "matchtime": 528.6400000000164, "event": "LACK_OF_PROGRESS", "payload": {"type": "robot", "robot_name": "Y1"}},
{"datetime": "2021-05-30T23:52:21.345437Z", "matchtime": 528.6400000000164, "event": "LACK_OF_PROGRESS", "payload": {"type": "robot", "robot_name": "Y2"}},
{"datetime": "2021-05-30T23:52:21.352880Z", "matchtime": 528.6400000000164, "event": "LACK_OF_PROGRESS", "payload": {"type": "robot", "robot_name": "Y3"}},
{"datetime": "2021-05-30T23:52:23.675768Z", "matchtime": 535.9360000000156, "event": "LACK_OF_PROGRESS", "payload": {"type": "ball"}},
{"datetime": "2021-05-30T23:52:26.136521Z", "matchtime": 543.7440000000156, "event": "LACK_OF_PROGRESS", "payload": {"type": "robot", "robot_name": "B1"}},
{"datetime": "2021-05-30T23:52:26.142683Z", "matchtime": 543.7440000000156, "event": "LACK_OF_PROGRESS", "payload": {"type": "robot", "robot_name": "B2"}},
{"datetime": "2021-05-30T23:52:26.149319Z", "matchtime": 543.7440000000156, "event": "LACK_OF_PROGRESS", "payload": {"type": "robot", "robot_name": "B3"}},
{"datetime": "2021-05-30T23:52:26.154470Z", "matchtime": 543.7440000000156, "event": "LACK_OF_PROGRESS", "payload": {"type": "robot", "robot_name": "Y1"}},
{"datetime": "2021-05-30T23:52:26.159699Z", "matchtime": 543.7440000000156, "event": "LACK_OF_PROGRESS", "payload": {"type": "robot", "robot_name": "Y2"}},
{"datetime": "2021-05-30T23:52:26.164173Z", "matchtime": 543.7440000000156, "event": "LACK_OF_PROGRESS", "payload": {"type": "robot", "robot_name": "Y3"}},
{"datetime": "2021-05-30T23:52:26.896612Z", "matchtime": 546.0480000000156, "event": "LACK_OF_PROGRESS", "payload": {"type": "ball"}},
{"datetime": "2021-05-30T23:52:30.159295Z", "matchtime": 556.1600000000155, "event": "LACK_OF_PROGRESS", "payload": {"type": "ball"}},
{"datetime": "2021-05-30T23:52:31.034108Z", "matchtime": 558.8480000000155, "event": "LACK_OF_PROGRESS", "payload": {"type": "robot", "robot_name": "B1"}},
{"datetime": "2021-05-30T23:52:31.040221Z", "matchtime": 558.8480000000155, "event": "LACK_OF_PROGRESS", "payload": {"type": "robot", "robot_name": "B2"}},
{"datetime": "2021-05-30T23:52:31.045292Z", "matchtime": 558.8480000000155, "event": "LACK_OF_PROGRESS", "payload": {"type": "robot", "robot_name": "B3"}},
{"datetime": "2021-05-30T23:52:31.049713Z", "matchtime": 558.8480000000155, "event": "LACK_OF_PROGRESS", "payload": {"type": "robot", "robot_name": "Y1"}},
{"datetime": "2021-05-30T23:52:31.054855Z", "matchtime": 558.8480000000155, "event": "LACK_OF_PROGRESS", "payload": {"type": "robot", "robot_name": "Y2"}},
{"datetime": "2021-05-30T23:52:31.060500Z", "matchtime": 558.8480000000155, "event": "LACK_OF_PROGRESS", "payload": {"type": "robot", "robot_name": "Y3"}},
{"datetime": "2021-05-30T23:52:33.464492Z", "matchtime": 566.2720000000156, "event": "LACK_OF_PROGRESS", "payload": {"type": "ball"}},
{"datetime": "2021-05-30T23:52:35.881156Z", "matchtime": 573.9520000000156, "event": "LACK_OF_PROGRESS", "payload": {"type": "robot", "robot_name": "B1"}},
{"datetime": "2021-05-30T23:52:35.887175Z", "matchtime": 573.9520000000156, "event": "LACK_OF_PROGRESS", "payload": {"type": "robot", "robot_name": "B2"}},
{"datetime": "2021-05-30T23:52:35.892602Z", "matchtime": 573.9520000000156, "event": "LACK_OF_PROGRESS", "payload": {"type": "robot", "robot_name": "B3"}},
{"datetime": "2021-05-30T23:52:35.897531Z", "matchtime": 573.9520000000156, "event": "LACK_OF_PROGRESS", "payload": {"type": "robot", "robot_name": "Y1"}},
{"datetime": "2021-05-30T23:52:35.902332Z", "matchtime": 573.9520000000156, "event": "LACK_OF_PROGRESS", "payload": {"type": "robot", "robot_name": "Y2"}},
{"datetime": "2021-05-30T23:52:35.909528Z", "matchtime": 573.9520000000156, "event": "LACK_OF_PROGRESS", "payload": {"type": "robot", "robot_name": "Y3"}},
{"datetime": "2021-05-30T23:52:36.774282Z", "matchtime": 576.3840000000156, "event": "LACK_OF_PROGRESS", "payload": {"type": "ball"}},
{"datetime": "2021-05-30T23:52:39.971334Z", "matchtime": 586.4960000000156, "event": "LACK_OF_PROGRESS", "payload": {"type": "ball"}},
{"datetime": "2021-05-30T23:52:40.772450Z", "matchtime": 589.0560000000156, "event": "LACK_OF_PROGRESS", "payload": {"type": "robot", "robot_name": "B1"}},
{"datetime": "2021-05-30T23:52:40.779309Z", "matchtime": 589.0560000000156, "event": "LACK_OF_PROGRESS", "payload": {"type": "robot", "robot_name": "B2"}},
{"datetime": "2021-05-30T23:52:40.785130Z", "matchtime": 589.0560000000156, "event": "LACK_OF_PROGRESS", "payload": {"type": "robot", "robot_name": "B3"}},
{"datetime": "2021-05-30T23:52:40.790297Z", "matchtime": 589.0560000000156, "event": "LACK_OF_PROGRESS", "payload": {"type": "robot", "robot_name": "Y1"}},
{"datetime": "2021-05-30T23:52:40.795587Z", "matchtime": 589.0560000000156, "event": "LACK_OF_PROGRESS", "payload": {"type": "robot", "robot_name": "Y2"}},
{"datetime": "2021-05-30T23:52:40.800289Z", "matchtime": 589.0560000000156, "event": "LACK_OF_PROGRESS", "payload": {"type": "robot", "robot_name": "Y3"}},
{"datetime": "2021-05-30T23:52:43.268849Z", "matchtime": 596.6080000000156, "event": "LACK_OF_PROGRESS", "payload": {"type": "ball"}},
{"datetime": "2021-05-30T23:52:44.315682Z", "matchtime": 600.0000000000156, "event": "MATCH_FINISH", "payload": {"total_match_time": 600, "score_yellow": 0, "score_blue": 0, "team_name_yellow": "i-bots 6", "team_name_blue": "ZTK Dubrovnik CRO team"}}]
